privateurl/__init__.py
privateurl/admin.py
privateurl/apps.py
privateurl/models.py
privateurl/settings.py
privateurl/signals.py
privateurl/tasks.py
privateurl/urls.py
privateurl/views.py
privateurl/migrations/0001_initial.py
privateurl/migrations/__init__.py
privateurl/tests/__init__.py
privateurl/tests/tests.py
settings/__init__.py
settings/base.py
settings/local.py
settings/testing.py
ddaemon_django_private_url-0.1.0.dist-info/LICENSE
ddaemon_django_private_url-0.1.0.dist-info/METADATA
ddaemon_django_private_url-0.1.0.dist-info/WHEEL
ddaemon_django_private_url-0.1.0.dist-info/top_level.txt
ddaemon_django_private_url-0.1.0.dist-info/RECORD
