Metadata-Version: 2.1
Name: ddaemon-django-private-url
Version: 0.1.0
Summary: Django Private URL
Home-page: https://github.com/asuvorov/ddaemon-django-private-url/
Author: Artem Suvorov
Author-email: artem.suvorov@gmail.com
License: GPLv3 License
Classifier: Development Status :: 4 - Beta
Classifier: Environment :: Console
Classifier: Environment :: Plugins
Classifier: Framework :: Django
Classifier: Framework :: Django :: 4.2
Classifier: Framework :: Pytest
Classifier: Intended Audience :: Developers
Classifier: Intended Audience :: Information Technology
Classifier: License :: OSI Approved :: GNU General Public License v3 (GPLv3)
Classifier: Natural Language :: English
Classifier: Operating System :: Microsoft :: Windows
Classifier: Operating System :: POSIX
Classifier: Operating System :: POSIX :: Linux
Classifier: Programming Language :: Python :: 3
Classifier: Programming Language :: Python :: 3.12
Classifier: Topic :: Scientific/Engineering
Classifier: Topic :: Security
License-File: LICENSE
